mcstatusio/BedrockServer.py
mcstatusio/JavaServer.py
mcstatusio/__init__.py
mcstatusio/constants.py
mcstatusio/error.py
mcstatusio-1.1.1.dist-info/licenses/LICENSE
mcstatusio-1.1.1.dist-info/METADATA
mcstatusio-1.1.1.dist-info/WHEEL
mcstatusio-1.1.1.dist-info/top_level.txt
mcstatusio-1.1.1.dist-info/RECORD
