Metadata-Version: 2.4
Name: mcstatusio
Version: 1.1.1
Summary: A Python wrapper for the mcstatus.io API.
Author-email: Rezn1r <rezn1r@proton.me>
License-Expression: MIT
Project-URL: Homepage, https://github.com/Rezn1r/mcstatusio
Project-URL: Repository, https://github.com/Rezn1r/mcstatusio
Project-URL: Issues, https://github.com/Rezn1r/mcstatusio/issues
Project-URL: Documentation, https://mcstatusio.readthedocs.io/
Classifier: Development Status :: 5 - Production/Stable
Classifier: Intended Audience :: Developers
Classifier: Programming Language :: Python :: 3.11
Classifier: Programming Language :: Python :: 3.12
Classifier: Programming Language :: Python :: 3.13
Classifier: Topic :: Software Development :: Libraries
Requires-Python: <3.14,>=3.11
License-File: LICENSE
Requires-Dist: httpx>=0.24.0
Requires-Dist: python-dotenv>=1.2.1
Dynamic: license-file
